ctl/__init__.py
ctl/auth.py
ctl/bin/ctl_venv_build
ctl/bin/ctl_venv_copy
ctl/bin/ctl_venv_sync
ctl/cli.py
ctl/config/__init__.py
ctl/config/schema.py
ctl/docs.py
ctl/events.py
ctl/exceptions.py
ctl/log.py
ctl/plugins/__init__.py
ctl/plugins/all.py
ctl/plugins/chain.py
ctl/plugins/changelog.py
ctl/plugins/command.py
ctl/plugins/config.py
ctl/plugins/copy.py
ctl/plugins/email.py
ctl/plugins/git.py
ctl/plugins/log.py
ctl/plugins/log_alert.py
ctl/plugins/log_git.py
ctl/plugins/log_user.py
ctl/plugins/pypi.py
ctl/plugins/release.py
ctl/plugins/repository.py
ctl/plugins/semver2.py
ctl/plugins/template.py
ctl/plugins/venv.py
ctl/plugins/version.py
ctl/plugins/version_base.py
ctl/plugins/walk_dir.py
ctl/util/__init__.py
ctl/util/git.py
ctl/util/template.py
ctl/util/versioning.py
ctl-1.2.0.dist-info/LICENSE
ctl-1.2.0.dist-info/METADATA
ctl-1.2.0.dist-info/WHEEL
ctl-1.2.0.dist-info/entry_points.txt
ctl-1.2.0.dist-info/RECORD
