Metadata-Version: 2.1
Name: ctl
Version: 1.2.0
Summary: Full control of your environment
Home-page: https://github.com/20c/ctl
License: Apache-2.0
Author: 20C
Author-email: code@20c.com
Requires-Python: >=3.9,<4.0
Classifier: Development Status :: 5 - Production/Stable
Classifier: Environment :: Console
Classifier: Intended Audience :: Developers
Classifier: License :: OSI Approved :: Apache Software License
Classifier: Programming Language :: Python :: 3
Classifier: Programming Language :: Python :: 3.9
Classifier: Programming Language :: Python :: 3.10
Classifier: Programming Language :: Python :: 3.11
Classifier: Programming Language :: Python :: 3.12
Classifier: Programming Language :: Python :: 3.8
Classifier: Topic :: Software Development
Classifier: Topic :: Software Development :: Build Tools
Classifier: Topic :: Software Development :: Documentation
Requires-Dist: GitPython (>=3.1.36)
Requires-Dist: confu (>=1.4)
Requires-Dist: grainy (>=1.4)
Requires-Dist: munge (>=1)
Requires-Dist: natsort (>=8)
Requires-Dist: ogr (>=0.46.0)
Requires-Dist: pluginmgr (>=1)
Requires-Dist: pydantic (>=2.3.0)
Requires-Dist: semver (<=3)
Project-URL: Repository, https://github.com/20c/ctl
